{"籤詩版本二": "ရှည်လျားသော နွေဦးမိုးသည် ကြည်လင်လာသောအခါ ကျောက်စိမ်း ယုန်နှင့် ရွှေကျီးကန်းတို့သည် တဖြည်းဖြည်း တောက်ပလာသည်။\nအဟောင်းတွေ ပျောက်ပြီး အသစ်တွေပေါ်လာတယ်။ နဂါးတံခါးကို တစ်ချက်ကြည့်လိုက်ပါ။", "詩意": "ဤ hexagram သည် ရှည်လျားသောမိုးနှင့် အစောပိုင်းအလင်းရောင်၏ သင်္ကေတဖြစ်သည်။\nအားလုံးစီစဉ်ထားတဲ့အတိုင်းပါပဲ။", "解曰": "ဘုရားများနှင့် ဗုဒ္ဓရုပ်ပွားတော်များက ကာကွယ်ထားသည်။ ဘေးဥပဒ်အန္တရာယ်မရှိပါ။ ခရီးစဉ် အေးချမ်းကြပါစေ။ အဆုံးတွင် ဂုဏ်ယူစွာဖြင့် ပြန်လာပါ။", "籤詩故事一": "◇ Jiang Taigong သည် ဘုရင် Wen နှင့် တွေ့ဆုံသည်။\nZhou မင်းဆက်။ Jiang Shang၊ ရည်မွန်နာမည် Ziya။ Ji လူမျိုး (အရှေ့တရုတ်ပင်လယ်ရှိ Xuzhou မှ)။ တာအိုအမည်မှာ Fei Xiong ဖြစ်ပြီး သူ၏ဘိုးဘေးများကို Lu (နေရာအမည်) ဖြင့် တံဆိပ်ခတ်ထားသောကြောင့် Lu Wang ဟုခေါ်သည်။\nShang မင်းဆက်ဘုရင် Zhou ရဲ့ ဒုက္ခရောက်ချိန်တွေကို ရှောင်ရှားဖို့အတွက် သူဟာ အရှေ့တရုတ်ပင်လယ်ရဲ့ ရေပြင်မှာ နေထိုင်ပြီး Weishui မြစ်ထဲမှာ ငါးဖမ်းခဲ့ပါတယ်။ ငါးမျှားချိတ်သည် ဖြောင့်ဖြောင့်ကြီး ငါးမျှားရန်မဟုတ်ဘဲ သီလရှိသော ၀န်ကြီးချုပ်ဖြစ်ရန်ဖြစ်သည်။\nZhou ဘုရင် Wen သည် ပညာရှိဖြစ်သည်ကို ကြားသိရပြီး သူ့ကို ဆရာ (ဝန်ကြီးချုပ်) အဖြစ် ခန့်အပ်ခဲ့သည်။ (ထိုအချိန်တွင် အသက်ရှစ်ဆယ်ရှိပြီ) နောက်ပိုင်းတွင် Zhou ဘုရင် Wu သည် Zhou ဘုရင်ကို တိုက်ခိုက်ပြီး Shang မင်းဆက်ကို ဖျက်ဆီးကာ Zhou မင်းဆက်ကို ထူထောင်ခဲ့သည်။ Wu က သူ့ကို Shangfu လို့ခေါ်တယ်။ သားဖြစ်သူ Ding Gong သည် Qi ၏ Marquis ဘွဲ့ကို ရရှိခဲ့သည်။\n(ဒီဇာတ်လမ်းရဲ့ အဓိကအချက်ကတော့ Weishui မြစ်မှာ ငါးမျှားဖို့ အချိန်အကြာကြီး စောင့်ခဲ့ရတဲ့ Jiang Taigong ဟာ ​​နောက်ဆုံးမှာ ပြဿနာကနေ လွတ်မြောက်ခဲ့ပြီး ဘုရင် Wen က ပြန်လည်အသုံးပြုခဲ့ပါတယ်။)", "聖意": "အိမ်ထဲမှာတော့ Zhongping ကိုယ်တိုင်က ကောင်းချီးပေးပြီး စည်းစိမ်ဥစ္စာတွေ ရပါစေလို့ ဆုတောင်းပေးပါတယ် အဆင်မပြေရင် အိမ်ထောင်ရေးက ကျပန်းပါပဲ။ Liujia အမျိုးသမီး လမ်းသွားလမ်းလာတွေက လယ်ကွင်းတွေကို ပိတ်ဆို့၊ ပိုးကောင်ခြောက်ကောင်ကို ပိတ်ဆို့ပြီး လူကို ရှာဖွေတာ၊ တရားစွဲတာ နောက်ကျတာနဲ့ ရွှေ့ပြောင်းနေထိုင်မှုတွေ ကံကောင်းစေတယ်။ Xingxing တောင်တွင် ပိုင်ဆိုင်မှု၊ ရောဂါနှင့် သင်္ချိုင်းများ ဆုံးရှုံးခဲ့သည်။", "古人": "Jiang Taigong သည် ဘုရင် Wen ကို တွေ့ဆုံသည်။", "第X籤": "နှစ်သောင်း ပထမ ထီပေါက်သည်။", "宮": "Tatsumi"}