{"籤詩版本二": "यिन और यांग का संयोजन हमेशा स्वर्ग द्वारा निर्धारित होता है। जब एक महिला किसी पुरुष से शादी करती है, तो यह एक खुशहाल शादी होती है।\nलेकिन ड्रैगन और सांप को मिलते देखकर, जिओंग जेन ड्रीम ऑर्केस्ट्रा में प्रवेश करता है और फिर से मिल जाता है", "詩意": "यह हेक्साग्राम यिन और यांग और दाओ के संयोजन का प्रतिनिधित्व करता है।\nसबकुछ ठीक होता है।", "解曰": "अपने दिल की सुनो। विवाह और गर्भावस्था. लाभदायक धन. खेत के रेशमकीटों के लिए अधिक लाभदायक।", "籤詩故事一": "◇ली डैन और ड्रैगन और फ़ीनिक्स सहयोग करते हैं\nली डैन तांग राजवंश के रुइज़ोंग बन गए, वू ज़ेटियन सिंहासन पर चढ़े, और सम्राट को एक सामान्य व्यक्ति के पद पर पदावनत कर दिया गया और वह ग्रामीण इलाकों में रहने लगे। उनकी मुलाकात हू फेंगजियाओ से हुई और उन्होंने शादी कर ली। लोककथाओं के अनुसार, उन दोनों में से प्रत्येक के भ्रूण के बेल्ट से आधा वर्गाकार सील निकाला गया था। \"फाइट सील\" पारित करने के बाद, उन्होंने साबित कर दिया कि वे एक हो सकते हैं और पति-पत्नी बन गए।\n(ड्रैगन रुइज़ॉन्ग को संदर्भित करता है, और फ़ीनिक्स हू फेंगजियाओ को संदर्भित करता है। इसका मतलब है कि विवाह स्वर्ग द्वारा निर्धारित किया जाता है।)", "聖意": "घर की सुरक्षा, स्वार्थ, धन, व्यापार, विवाह, लिउजिया, खेतों में पुरुष पैदल यात्री, रेशमकीट समृद्ध हैं, जानवर समृद्ध हैं, लोगों की तलाश कर रहे हैं, मुकदमे उचित हैं, प्रवास समृद्ध है, खोई हुई संपत्ति मिल जाती है, बीमारियों का सामना करना पड़ता है, अच्छा है उपाय मिल जाते हैं, पहाड़ और कब्रें सौभाग्य हैं", "古人": "ली डैन ड्रैगन और फीनिक्स सहयोग", "第X籤": "इक्कीसवें पर हस्ताक्षर करें", "宮": "Tatsumi"}