{"籤詩版本二": "शानदार चीड़ और सरू फल-फूल रहे हैं, और बारिश, बर्फ, हवा और ठंढ सभी चीजें हैं।\nभविष्य अचानक बड़े काम का हो जाएगा और प्रसिद्धि स्तंभ बन जाएगी।", "詩意": "यह हेक्साग्राम चीड़ और सरू के घने जंगल की छवि है।\nहर चीज़ में बड़प्पन है.", "解曰": "सड़क पर शुभकामनाएँ. आजीवन सराहनीय सेवा। खेत के रेशमकीट पक गये हैं। परिवार समृद्ध है.", "籤詩故事一": "◇फैन वेनझेंग ने दलिया बनाने और खींचने का फैसला किया\nसांग राजवंश के एक प्रसिद्ध अधिकारी, फैन झोंगयान, जब वह छोटे थे, एक गरीब परिवार से आते थे। उन्होंने चांगबाई पर्वत में एक भिक्षु के निवास में अध्ययन किया। उन्होंने हर दिन दो लीटर बाजरा के साथ दलिया पकाया। रात भर जमने के बाद, उन्होंने इसे काट दिया चाकू से चार टुकड़े कर दिये, दो-दो टुकड़े सुबह-शाम खाये और कुछ अचार भी काट कर खाया.\nइसका उपयोग किसी ऐसे व्यक्ति का वर्णन करने के लिए किया जाता है जो कठिनाइयों से नहीं डरता, कड़ी मेहनत करता है और अंततः बड़े काम की प्रतिभा बन जाता है।\nहैरो को काटकर दलिया बना लें", "聖意": "जियाझाई स्वयं के लिए शुभ है, धन की तलाश, शांति, व्यापार, विवाह, सफलता, लिउजिया, पुरुष पैदल यात्री, विश्वास क्षेत्र, रेशम के कीड़े, छह पशुधन, क्षति, लोगों का पता लगाना, मुकदमे, प्रवास, खोई हुई संपत्ति, बीमारी, अनशन कब्र, शुभता", "古人": "फैन वेन्झेंग ने दलिया बनाने और खींचने का फैसला किया", "第X籤": "आठवाँ लक्षण", "宮": "बदसूरत महल"}