{"籤詩版本二": "അയാൾക്ക് ഒരു മനുഷ്യനെ തിരികെ നൽകാനായി പാറക്കടിയിൽ കൊത്തിയെടുത്ത ടോറി ഗേറ്റിലേക്ക് എറിഞ്ഞു.\nനേരത്തെ പ്ലാൻ ചെയ്താൽ ആർക്കൊക്കെ കിട്ടും?ലോകം ചുറ്റി സഞ്ചരിക്കാൻ ആരുമില്ല.", "詩意": "ഈ ഹെക്സാഗ്രാം ഒരു വെങ്കല പക്ഷിയുടെ ചിത്രം ഒരു പാറയിൽ ഇടുന്നു.\nഎല്ലാത്തിലും ഭാഗ്യത്തിന്റെ അടയാളം.", "解曰": "മത്സ്യമില്ലാതെ കഴിക്കുക. ശുദ്ധവും സന്തോഷവും ഉള്ളത് ദരിദ്രമാണ്. ടെട്രാ പാക്കിനായി കാത്തിരിക്കുക. അധികാരവും ആളുകളും.", "籤詩故事一": "◇ദയ കർത്താവിനെ കണ്ടുമുട്ടുന്നു\nടാങ് രാജവംശത്തിൽ, Xue Li (614-683), കടപ്പാട് പേര് Rengui, Longmen, Jiangzhou (ഇപ്പോൾ Hejin, Shanxi) ജനിച്ചു.\nXue Rengui മൂന്ന് തവണ സൈന്യത്തിൽ ചേർന്നു, ഒരു ഭക്ഷ്യ സൈനികനായി മാത്രം സേവനമനുഷ്ഠിച്ചു.\nതാങ് രാജവംശത്തിലെ ടൈസോങ്ങ് ചക്രവർത്തി (ലി ഷിമിൻ) ഗൈസുവാൽ പിന്തുടരപ്പെട്ടപ്പോൾ, അവൻ അപകടത്തിൽ പെട്ടു, റെൻഗുയി രക്ഷപ്പെടുത്തി.\nഅതായത്, ടാങ് രാജവംശത്തിലെ ടൈസോങ് ചക്രവർത്തി അദ്ദേഹത്തെ മാർഷൽ എന്ന് നാമകരണം ചെയ്തു, കിഴക്കോട്ട് സൈന്യത്തെ നയിക്കുകയും നിരവധി സൈനിക ചൂഷണങ്ങൾ നേടുകയും ചെയ്തു.", "聖意": "വീടു തനിക്കുതന്നെ പ്രതികൂലമാണ്.മംഗളകരം, ഐശ്വര്യം, ഐശ്വര്യം, ഭാഗ്യം, കച്ചവടം, വിവാഹം സാധാരണം, ലിയുജിയ സുരക്ഷിതം, വയലുകൾക്ക് സമീപം, പട്ടുനൂൽപ്പുഴുക്കൾ നേരത്തെ നട്ടു.ആറ് കന്നുകാലികൾക്ക് നാശം.ആളുകൾ കാണാതാകുന്നു.പൊതു വ്യവഹാരങ്ങൾ ന്യായം.ദേശാടനം ശുഭം.നഷ്ടപ്പെട്ട സ്വത്ത് ശുഭം.രോഗങ്ങൾ കണ്ടുപിടിക്കുക.സമാധാനത്തിനായി മലകല്ലറയിലേക്ക് അയക്കുക.", "古人": "റെൻഗുയി കർത്താവിനെ കണ്ടുമുട്ടുന്നു", "第X籤": "ആറാമത്തെ ലോട്ടറി", "宮": "വൃത്തികെട്ട കൊട്ടാരം"}