{"籤詩版本二": "இம்மார்டலிட்டி கற்க நேராக இம்மார்டல் ராக் செல்லுங்கள். இந்த அறிவு பேரரசரால் அறிவிக்கப்பட்டதும்,\nநீல வானம், சூரியன் மற்றும் சந்திரன் எப்போதும் பிரகாசமாக பிரகாசிக்கின்றன, மேலும் நேர்மையான இதயத்தின் புகழ் உலகம் முழுவதும் பரவுகிறது.", "詩意": "இந்த ஹெக்ஸாகிராம் உன்னத மக்களிடமிருந்து வழிகாட்டுதலைப் பெறுவதற்கான அடையாளமாகும்.\nஎல்லாம் ஒன்றாக நன்றாக செல்கிறது.", "解曰": "தொடக்கமும் முடிவும் உண்டு. மேற்கு அல்லது கிழக்கு நோக்கி செல்ல வேண்டாம். உங்கள் இதயத்தைப் பயன்படுத்துங்கள். பல உன்னத மனிதர்கள் உள்ளனர்.", "籤詩故事一": "◇Liu Zhiyuan இராணுவத்திற்கு மாறினார்\nலியு ஷியுவான் (ஜியுவான்) ஷட்டாவோ (ஷாதுவோ பழங்குடியினர்) சேர்ந்தவர்.\nLiu Zhiyuan மற்றும் அவரது மனைவி Li Sanniang அவரது மாமா வீட்டில் வசித்து வந்தனர்.அவரது மாமா Liu Zhiyuan (Zhiyuan) ஏழை என்று சந்தேகப்பட்டார், எனவே அவர் Zhiyuan முலாம்பழம் தோட்டத்திற்கு செல்ல தூண்டினார், லியுவை இரண்டு முலாம்பழம் ஆவிகள் சாப்பிடும் என்று நம்பினார். Zhiyuan எடுத்துக்கொண்டார். இரவில் ஒரு துப்பாக்கி, முலாம்பழம் ஆவிகளுடன் சண்டையிட்டு, நிலத்தடிக்குச் சென்று, நிலத்தைத் தோண்டி, வாள் மற்றும் போர் புத்தகத்தைப் பெறுங்கள்.\nஅவர் தனது வாள் மற்றும் இராணுவ திறன்களை எடுத்து, தனது மனைவியிடம் விடைபெற்று இராணுவத்தில் சேர்ந்தார். அவர் யு க்சுனிடம் தஞ்சம் புகுந்து, சமாதானப்படுத்தும் தூதுவராக பணியாற்றினார்.\nகிதான் ஜின் வம்சத்தை அழித்தார், மத்திய சமவெளியை எஜமானர் இல்லாமல் விட்டுவிட்டார்.ஜின்யாங்கில் ஜியுவான் பேரரசர் ஆனார்.\nநாடு பின்னர் ஹான் வம்சமாக மாற்றப்பட்டது. இது இன்னும் சகாப்தத்தை மாற்றாமல் Tianfu (ஆண்டு பெயர்) என்று அழைக்கப்படுகிறது.", "聖意": "வீடு பாதுகாப்பானது, சுயநலம், பணம் நல்லது, வியாபாரம் நல்லது, திருமணம் நல்லது, தம்பதிகள் திருமணம் செய்து கொண்டனர், ஆண் பயணி வயலுக்குத் திரும்புகிறார், பட்டுப்புழுக்கள் பாதி அறுவடை, ஆறு விலங்குகள் வெற்றி , ஆள் கண்டு, வழக்கு வெற்றி, இடம்பெயர்தல் நலம், இழந்த சொத்து நலம், நோய் அன்ஷன், கல்லறை நன்று", "古人": "Liu Zhiyuan இராணுவத்திற்கு மாறினார்", "第X籤": "எண்பதாம் அடையாளம்", "宮": "வெய் காங்"}