{"籤詩版本二": "आकाशात चंद्र चमकतो आणि घर शांत आहे.अचानक ढग आणि धुक्याचा फटका बसतो आणि कोमात जातो.\nकृपया मनःशांतीसाठी प्रार्थना करा, युनक्सिया पावडर, यावेळी दानधर्म बदला, आणि घरात एक पुस्तक लिहा.", "詩意": "या हेक्साग्राममध्ये, ढग आणि धुके चंद्र झाकतात.\nजरी गोष्टी कार्य करत नसल्या तरीही जुन्या मार्गांवर रहा.", "籤詩故事一": "◇ तो Wenxiu मारला गेला\nमिंग राजवंशाच्या जियाजिंग काळात, हे वेन्क्शिउ यांना विश्वासघातकी मंत्र्यांनी बनवले आणि त्यांचे कुटुंब अडचणीत आले.त्याला वेन्क्शिउ यांना पंतप्रधानांची राणी लॅन यिंग यांनी मदत केली आणि त्या दोघांनी खाजगीरित्या लग्न केले. तो Wenxiu या दादागिरी झांग तांग यांनी खोटे आरोप केले आणि तुरुंगात टाकले. नंतर त्याची सुटका करण्यात आली आणि परीक्षा उत्तीर्ण झाल्यावर राज्यपाल झाला. Wenxiu ने वांग लॅनिंगचा ठावठिकाणा शोधून काढला आणि ते शोधण्यासाठी भविष्यवेत्ता म्हणून कपडे घातले. शेवटी दोघे पुन्हा एकत्र आले आणि झांग तांगला फाशी देण्यात आली.", "聖意": "घरी अस्वस्थता, मी संरक्षणासाठी प्रार्थना करतो, आर्थिक अडचणी, व्यवसायातील अडचणी, लग्नातील अडचणी, लिउजियाची कमतरता, पादचाऱ्यांना शेतात अडथळा, रेशीम किड्याचे नुकसान, पशुधनाचे नुकसान, हरवलेली माणसे, सार्वजनिक खटले, स्थलांतर, हरवलेली मालमत्ता, आजारपण, यानान पर्वत थडग्यासाठी दुरुस्त करणे", "古人": "तो Wenxiu मारला गेला", "第X籤": "लोट अडतीस", "宮": "शेन गोंग"}