{"籤詩版本二": "कॅन्ग्लॉन्ग एकोणिसाव्या रक्षकांची जाणीव: एका महिलेने दुसरे पतीशी लग्न केले\nएक धनुष्य आणि दोन बाणांसह, डायनासोर लगेच शांततेत राहतील", "詩意": "हे हेक्साग्राम दोन बाण धरलेल्या धनुष्यासारखे आहे.\nजर सर्व काही जुळले तर ते शुभ होईल.", "解曰": "फार जड नाही. नशीब. झेन लिउझोंग उघडले. सावध राहण्याचा सल्ला दिला जातो.", "籤詩故事一": "◇ वेनजुन शियांगरूला भेट देतात\nझुओ वेनजुन ही सिचुआन प्रांतातील लिनकिओंग येथील धनाढ्य व्यापारी झुओ वांग यांच्या नातवाची मुलगी होती.ती संगीतात पारंगत होती आणि तिचे साहित्यिक नाव होते. ती सोळा वर्षांची असताना तिचे लग्न झाले.काही वर्षांनंतर तिच्या पतीचे निधन झाले आणि ती विधवा म्हणून राहण्यासाठी तिच्या जन्मदात्या कुटुंबात परतली.\nएके दिवशी, सिमा झियांगरू झुओ वांग्सुनच्या घरी मेजवानीसाठी गेली. झुओ वेनजुन नुकतीच विधवा झाल्याचे कळल्यावर त्याने आपले प्रेम व्यक्त करण्यासाठी \"फिनिक्स सीकिंग द फिनिक्स\" हे गाणे वाजवले. झुओ वेनजुनने सिमा शिआंगरूबद्दल आधीच ऐकले होते आणि या मेजवानीने तो सिमा शिआंगरूकडे आणखी आकर्षित झाला. दुसरीकडे, सिमा झियांगरूच्या मेजवानीच्या नंतर, झूओ वेनजुनच्या वैयक्तिक दासीला लाच देण्यासाठी त्याने लगेच भरपूर पैसे खर्च केले आणि तिला सिमा झियांगरूचे झुओ वेनजुनवरील प्रेम सांगण्यास सांगितले. झुओ वेनजुनला मोलकरणीद्वारे सिमा झियांगरूच्या प्रेमाविषयी कळल्यानंतर, तो ताबडतोब सिमा झियांगरू राहत असलेल्या सरायकडे गेला. झुओ वेनजुनचे आगमन पाहून, सिमा झियांगरू लगेचच तिच्यासोबत चेंगडू येथील त्याच्या गावी रात्रभर पळून गेली.\nजेव्हा ते चेंगडूमध्ये होते, तेव्हा ते जोडपे निराधार होते आणि उदरनिर्वाहासाठी एक छोटे हॉटेल उघडण्यासाठी लिनकिओंगला परतावे लागले. झुओ वेनजुन वाईन विकत आणि सिमा झियांगरू भांडी धुत. ते गरीब जीवन जगत होते. झुओ वेनजुनचे वडील, झुओ वांग्सुन यांना हे समजल्यानंतर, त्यांनी सहमती दर्शवली आणि त्यांच्या मित्रांच्या सल्ल्यानुसार त्यांना निधी दिला, जेणेकरून सिमा झियांगरू आणि झुओ वेनजुन राहण्यासाठी चेंगडूला परतले आणि नंतर ते श्रीमंत झाले.", "聖意": "घर आणि मालमत्तेची हानी, स्वतःचे हक्क आणि चूक, संपत्ती मिळवणे, श्रम व्यवहार, पुनर्विवाहापासून संरक्षण करणे.", "古人": "वेनजुन यांनी शियांगरूला भेट दिली", "第X籤": "एकहत्तर विजयी लॉटरी", "宮": "तत्सुमी"}