{"籤詩版本二": "ਵ੍ਹੇਲ ਅਟੱਲ ਰਹਿੰਦੀ ਹੈ ਅਤੇ ਨਦੀ ਦੀ ਰਾਖੀ ਕਰਦੀ ਹੈ। ਇਹ ਉੱਚੀ ਨਹੀਂ ਉੱਠ ਸਕਦੀ ਅਤੇ ਉੱਚੀ ਉਮੀਦ ਨਹੀਂ ਰੱਖ ਸਕਦੀ।\nਭਵਿੱਖ ਵਿੱਚ ਅਸਧਾਰਨ ਤਬਦੀਲੀਆਂ, ਜ਼ੂ ਜੂਨ ਡਰੈਗਨ ਗੇਟ ਉੱਤੇ ਛਾਲ ਮਾਰਦਾ ਹੈ", "詩意": "ਇਹ ਹੈਕਸਾਗ੍ਰਾਮ ਵ੍ਹੇਲ ਦੀ ਨਾ ਬਦਲੀ ਤਸਵੀਰ ਦਿਖਾਉਂਦਾ ਹੈ।\nਸਮਾਂ ਆਉਣ ਤੱਕ ਸਬਰ ਰੱਖੋ।", "解曰": "ਤੁਹਾਨੂੰ ਇਹ ਸਹਿਣਾ ਪਵੇਗਾ। ਧੀਰਜ ਅਤੇ ਧੀਰਜ ਰੱਖੋ. ਸਮਾਂ ਆਉਣ ਤੱਕ ਉਡੀਕ ਕਰਨੀ ਪਵੇਗੀ। ਪ੍ਰਸਿੱਧੀ ਅਜੇ ਵੀ ਉਥੇ ਹੈ.", "籤詩故事一": "◇ ਸੂ ਕਿਨ ਬੁ ਦੀ\nਜੰਗੀ ਰਾਜਾਂ ਦੀ ਮਿਆਦ ਦੇ ਦੌਰਾਨ, ਸੁ ਕਿਨ, ਲੁਓਯਾਂਗ ਦੇ ਇੱਕ ਮੂਲ ਨਿਵਾਸੀ, ਨੇ ਆਪਣੇ ਅਧਿਆਪਕ ਵਜੋਂ ਗੁਈ ਗੁਜ਼ੀ ਦੀ ਪੂਜਾ ਕੀਤੀ।\nਸੂ ਕਿਨ ਨੇ ਕਿਨ ਦੇ ਰਾਜੇ ਦੀ ਪੈਰਵੀ ਕੀਤੀ ਅਤੇ ਬਾਰਾਂ ਵਾਰ ਲਿਖਿਆ, ਪਰ ਕਿਨ ਦੇ ਰਾਜੇ ਨੇ ਉਸਦੀ ਦਲੀਲ ਨੂੰ ਸਵੀਕਾਰ ਨਹੀਂ ਕੀਤਾ। ਜਦੋਂ ਉਹ ਘਰ ਪਰਤਿਆ ਤਾਂ ਉਸਦਾ ਫਰ ਕੋਟ ਪਾਟਿਆ ਹੋਇਆ ਸੀ ਅਤੇ ਉਸਦੇ ਕੋਲ ਪੈਸੇ ਖਤਮ ਹੋ ਚੁੱਕੇ ਸਨ, ਉਹ ਦਰਵਾਜ਼ੇ 'ਤੇ ਹੰਗਾਮਾ ਕਰਦਾ ਹੋਇਆ ਪਹੁੰਚਿਆ, ਉਸਦੀ ਪਤਨੀ ਨੇ ਉਸਨੂੰ ਨਜ਼ਰਅੰਦਾਜ਼ ਕੀਤਾ ਅਤੇ ਉਸਦੀ ਭਰਜਾਈ ਨੇ ਉਸਦੇ ਲਈ ਖਾਣਾ ਨਹੀਂ ਬਣਾਇਆ।\nਸੂ ਕਿਨ ਸ਼ਰਮਿੰਦਾ ਅਤੇ ਗੁੱਸੇ ਵਿੱਚ ਸੀ, ਇਸ ਲਈ ਉਸਨੇ ਤਾਇਗੋਂਗ ਯਿਨ ਫੂ (ਯੁੱਧ ਦੀ ਕਲਾ ਬਾਰੇ ਕਿਤਾਬ) ਪ੍ਰਾਪਤ ਕੀਤੀ ਅਤੇ ਇਸਨੂੰ ਗੁੱਸੇ ਵਿੱਚ ਪੜ੍ਹਿਆ। ਜਦੋਂ ਤੁਸੀਂ ਉਲਝਣ ਅਤੇ ਆਲਸੀ ਮਹਿਸੂਸ ਕਰਦੇ ਹੋ, ਤਾਂ ਆਪਣੇ ਪੱਟ ਨੂੰ ਇੱਕ awl ਨਾਲ ਚੁਭੋ ਅਤੇ ਜਦੋਂ ਇਹ ਦਰਦ ਹੋਵੇ ਤਾਂ ਦੁਬਾਰਾ ਪੜ੍ਹੋ।\nਬਾਅਦ ਵਿੱਚ, ਹੀ ਕੌਂਗ (ਹੀ ਜ਼ੋਂਗ) ਦੇ ਸਿਧਾਂਤ ਦੀ ਵਰਤੋਂ ਛੇ ਦੇਸ਼ਾਂ ਨੂੰ ਕਿਨ ਦੇ ਵਿਰੁੱਧ ਇੱਕਜੁੱਟ ਕਰਨ ਲਈ ਕੀਤੀ ਗਈ। ਉਸਨੇ ਰਾਜਾ ਝਾਓ ਦੀ ਪੈਰਵੀ ਕੀਤੀ ਅਤੇ ਛੇ ਦੇਸ਼ਾਂ ਦੇ ਪ੍ਰਧਾਨ ਮੰਤਰੀ ਬਣੇ।", "聖意": "ਮੈਂ ਘਰ ਵਿੱਚ ਬੇਚੈਨ ਹਾਂ, ਮੈਂ ਅਜੇ ਵੀ ਦੌਲਤ ਦੀ ਭਾਲ ਕਰਨਾ ਚਾਹੁੰਦਾ ਹਾਂ, ਬਦਕਿਸਮਤੀ, ਲੈਣ-ਦੇਣ, ਵਿਆਹ ਔਖਾ ਹੈ, ਲਿਉਜੀਆ ਪੈਦਲ ਚੱਲਣ ਵਾਲਿਆਂ ਲਈ ਵਰਦਾਨ ਹੈ, ਸੁਰੱਖਿਅਤ ਖੇਤ, ਰੇਸ਼ਮ ਦੇ ਕੀੜੇ ਚੰਗੇ ਹਨ, ਛੇ ਜਾਨਵਰ ਅਣਸੁਖਾਵੇਂ ਹਨ, ਲਾਪਤਾ ਲੋਕ, ਲੋਕ ਮੁਕੱਦਮੇ ਅਤੇ ਪਰਵਾਸ, ਗੁਆਚ ਗਏ ਹਨ ਚੀਜ਼ਾਂ, ਦੱਖਣ-ਪੂਰਬੀ ਬਿਮਾਰੀਆਂ, ਸੁਰੱਖਿਆ ਲਈ ਪ੍ਰਾਰਥਨਾ, ਪਹਾੜ ਅਤੇ ਕਬਰਾਂ।", "古人": "ਸੁ ਕਿਨ ਬੁ ਦੀ", "第X籤": "ਦੂਜੀ ਲਾਟਰੀ (ਲਾਟਰੀ ਜਿੱਤਣਾ)", "宮": "ਬੱਚੇਦਾਨੀ"}