{"籤詩版本二": "ਮੈਨੂੰ ਸੁਪਨੇ ਵਿੱਚ ਇੱਕ ਖਜ਼ਾਨਾ ਮਿਲਿਆ ਅਤੇ ਅਣਜਾਣ ਜਾਗ ਗਿਆ ਮੈਂ ਸੋਚਿਆ ਕਿ ਨਨਸ਼ਾਨ ਸਿਰਫ ਇੱਕ ਕੁੰਡਲੀ ਸੀ.\nਜੇ ਤੁਸੀਂ ਵਿਆਹ ਅਤੇ ਬੀਮਾਰੀ ਬਾਰੇ ਪੁੱਛਦੇ ਹੋ, ਤਾਂ ਇਕ ਦੂਜੇ ਦਾ ਸਮਰਥਨ ਕਰਨ ਦੇ ਤਰੀਕੇ ਨਾ ਲੱਭੋ।", "詩意": "ਇਹ ਹੈਕਸਾਗ੍ਰਾਮ ਇੱਕ ਸੁਪਨੇ ਵਿੱਚ ਖਜ਼ਾਨਾ ਪ੍ਰਾਪਤ ਕਰਨ ਦੇ ਪ੍ਰਤੀਕ ਨੂੰ ਦਰਸਾਉਂਦਾ ਹੈ.\nਸਭ ਕੁਝ ਵਿਅਰਥ ਹੈ।", "解曰": "ਚੀਜ਼ਾਂ ਪਾਣੀ ਵਿੱਚ ਹਨ. ਆਕਾਰ ਅਤੇ ਸ਼ੈਡੋ ਦੀ ਲੰਬਾਈ। ਸਾਰੇ ਦ੍ਰਿੜ੍ਹ ਹਨ। ਚਰਚਾ ਕਰਨ ਦੀ ਲੋੜ ਨਹੀਂ।", "籤詩故事一": "◇ਮਾ ਚਾਓ ਕਾਓ ਦਾ ਪਿੱਛਾ ਕਰਦਾ ਹੈ\nਮਾ ਚਾਓ (176-222), ਸ਼ਿਸ਼ਟਾਚਾਰੀ ਨਾਮ ਮੇਂਗਕੀ, ਫੁਫੇਂਗ ਮਾਓਲਿੰਗ (ਹੁਣ ਜ਼ਿੰਗਪਿੰਗ, ਸ਼ਾਂਕਸੀ ਪ੍ਰਾਂਤ ਦੇ ਉੱਤਰ-ਪੂਰਬ ਵਿੱਚ) ਦਾ ਵਸਨੀਕ ਸੀ। ਉਹ ਹਾਨ ਰਾਜਵੰਸ਼ ਦੇ ਅੰਤ ਵਿੱਚ ਅਤੇ ਤਿੰਨ ਰਾਜਾਂ ਦੇ ਸਮੇਂ ਵਿੱਚ ਸ਼ੂ ਹਾਨ ਰਾਜਵੰਸ਼ ਦਾ ਇੱਕ ਮਸ਼ਹੂਰ ਜਰਨੈਲ ਸੀ।\nਤਿੰਨ ਰਾਜਾਂ ਦੇ ਸਮੇਂ ਦੌਰਾਨ, ਕਾਓ ਕਾਓ ਨੇ ਮਾ ਚਾਓ ਦੇ ਪਿਤਾ ਨੂੰ ਮਾਰ ਦਿੱਤਾ। ਮਾ ਚਾਓ ਨੇ ਬਦਲਾ ਲਿਆ ਅਤੇ ਕਾਓ ਕਾਓ 'ਤੇ ਹਮਲਾ ਕੀਤਾ, ਪਰ ਕਾਓ ਕਾਓ ਹਾਰ ਗਿਆ ਅਤੇ ਭੱਜ ਗਿਆ।\nਮਾ ਚਾਓ ਦੇ ਸਿਪਾਹੀਆਂ ਦੁਆਰਾ ਪਛਾਣੇ ਨਾ ਜਾਣ ਲਈ, ਕਾਓ ਕਾਓ ਨੇ ਆਪਣੀ ਲਾਲ ਕਮੀਜ਼ ਲਾਹ ਦਿੱਤੀ, ਆਪਣੀ ਦਾੜ੍ਹੀ ਛੋਟੀ ਕਰ ਦਿੱਤੀ ਅਤੇ ਘੋੜੇ 'ਤੇ ਭੱਜ ਗਿਆ।\nਨਾਜ਼ੁਕ ਪਲ ਵਿੱਚ, ਕਾਓ ਹਾਂਗ ਸਮੇਂ ਸਿਰ ਆਪਣੀਆਂ ਫੌਜਾਂ ਨਾਲ ਪਹੁੰਚਿਆ, ਮਾ ਚਾਓ ਨੂੰ ਰੋਕਿਆ, ਅਤੇ ਕਾਓ ਕਾਓ ਦੀ ਜ਼ਿੰਦਗੀ ਨੂੰ ਨਰਕ ਦੇ ਦਰਵਾਜ਼ੇ ਤੋਂ ਬਚਾਇਆ।\n(ਇਹ ਕਹਾਣੀ ਇੱਕ ਅਲੰਕਾਰ ਹੈ ਕਿ ਕਿਵੇਂ ਕੋਈ ਆਪਣੀ ਪ੍ਰਸਿੱਧੀ ਅਤੇ ਰੁਤਬਾ ਛੱਡ ਕੇ ਖ਼ਤਰੇ ਤੋਂ ਬਚ ਸਕਦਾ ਹੈ।)", "聖意": "ਜੇਕਰ ਤੁਹਾਡੇ ਘਰ ਦੀ ਹਾਲਤ ਠੀਕ ਨਹੀਂ ਹੈ ਤਾਂ ਪੈਸੇ ਮੰਗਣ, ਲੈਣ-ਦੇਣ ਵਿੱਚ ਅੜਿੱਕਾ ਪਾਉਣ ਜਾਂ ਵਿਆਹ ਵਿੱਚ ਮੁਸ਼ਕਲ ਆਉਣ ਤੋਂ ਸਾਵਧਾਨ ਰਹੋ। ਪੈਦਲ ਚੱਲਣ ਵਾਲਿਆਂ ਲਈ ਅਸੀਸਾਂ ਦੀ ਅਰਦਾਸ ਕਰੋ। ਰੇਸ਼ਮ ਦੇ ਕੀੜੇ ਖੇਤਾਂ ਵਿੱਚ ਖੜੋਤੇ ਹਨ। ਛੇ ਪਸ਼ੂ ਖੜੋਤ ਹਨ। ਲੋਕਾਂ ਦੀ ਭਾਲ ਵਿੱਚ। ਜਨਤਕ ਮੁਕੱਦਮੇ। ਨੁਕਸਾਨ। ਪਰਵਾਸ। ਚੰਗੀ ਕਿਸਮਤ। ਗੁਆਚੀ ਜਾਇਦਾਦ। ਖਾਲੀ ਬਿਮਾਰੀਆਂ। ਰੱਬ ਦੀ ਰੱਖਿਆ ਲਈ ਪ੍ਰਾਰਥਨਾ ਕਰੋ। ਪਹਾੜ ਅਤੇ ਕਬਰਾਂ ਬੇਚੈਨ ਹਨ।", "古人": "ਮਾ ਚਾਓ ਕਾਓ ਦਾ ਪਿੱਛਾ ਕਰਦਾ ਹੈ", "第X籤": "ਲੋਟ 54ਵਾਂ", "宮": "ਬੱਚੇਦਾਨੀ"}