{"籤詩版本二": "នៅពេលដែលភ្លៀងនិទាឃរដូវដ៏វែងចាប់ផ្តើមស្រឡះ ទន្សាយ Jade និងក្អែកមាសកាន់តែភ្លឺឡើងបន្តិចម្តងៗ\nរឿងចាស់បាត់ របស់ថ្មីលេចចេញមក ចាំមើលមុខមាត់ទ្វារនាគ។", "詩意": "hexagram នេះ​ជា​និមិត្ត​រូប​នៃ​ភ្លៀង​ធ្លាក់​យ៉ាង​យូរ និង​ពន្លឺ​ដំបូង។\nអ្វីៗដំណើរការទៅតាមការគ្រោងទុក។", "解曰": "ការពារដោយព្រះ និងព្រះពុទ្ធ។ មិនមានគ្រោះថ្នាក់នៃគ្រោះមហន្តរាយទេ។ សូមអោយការធ្វើដំណើរប្រកបដោយសុខសន្តិភាព។ ត្រលប់មកវិញដោយកិត្តិយសនៅទីបញ្ចប់។", "籤詩故事一": "◇ Jiang Taigong ជួបស្តេច Wen\nរាជវង្សចូវ។ Jiang Shang, ឈ្មោះគួរសម Ziya ។ ប្រជាជន Ji (មកពី Xuzhou នៅសមុទ្រចិនខាងកើត) ។ ឈ្មោះតាវគឺ Fei Xiong ហើយបុព្វបុរសរបស់គាត់ត្រូវបានផ្សាភ្ជាប់នៅក្នុង Lu (ឈ្មោះទីកន្លែង) ដូច្នេះគាត់ត្រូវបានគេហៅថា Lu Wang ផងដែរ។\nដើម្បី​គេច​ពី​គ្រា​លំបាក​របស់​ស្តេច Zhou នៃ​រាជវង្ស Shang ព្រះអង្គ​បាន​រស់នៅ​ក្បែរ​សមុទ្រ​ចិន​ខាង​កើត ហើយ​បាន​នេសាទ​ត្រី​នៅ​ទន្លេ Weishui ។ ស្ទូច​ត្រី​ត្រង់​បំណង​មិន​ចង់​ស្ទូច​ទេ គឺ​ចង់​ធ្វើ​នាយករដ្ឋមន្ត្រី​ប្រកបដោយ​គុណធម៌។\nស្តេច Wen នៃ Zhou បានឮថាគាត់មានប្រាជ្ញាហើយបានជួលគាត់ជាគ្រូរបស់គាត់ (នាយករដ្ឋមន្ត្រី) ។ (គាត់មានអាយុប៉ែតសិបឆ្នាំនៅពេលនោះ) ក្រោយមកស្តេច Wu នៃ Zhou បានវាយប្រហារស្តេច Zhou បំផ្លាញរាជវង្ស Shang និងបង្កើតរាជវង្ស Zhou ។ ស្តេច Wu ហៅគាត់ថា Shangfu ។ កូនប្រុសរបស់គាត់ Ding Gong បានទទួលងារជា Marquis of Qi ។\n(ការផ្តោតអារម្មណ៍នៃរឿងនេះ៖ Jiang Taigong ដែលបានរង់ចាំនេសាទនៅទន្លេ Weishui អស់រយៈពេលជាយូរមកហើយ ទីបំផុតបានរួចផុតពីបញ្ហា ហើយត្រូវបានស្តេច Wen ប្រើឡើងវិញ)។", "聖意": "នៅក្នុងផ្ទះ Zhongping ខ្លួនឯងបួងសួងសុំពរជ័យ និងទ្រព្យសម្បត្តិ ពេលគ្មានការព្រមព្រៀងគ្នា អាពាហ៍ពិពាហ៍ក៏ចៃដន្យ Liujia ស្ត្រីថ្មើរជើងបិទវាលស្រែ ដង្កូវនាងរារាំងហ្វូងសត្វទាំងប្រាំមួយ រារាំងការស្វែងរកមនុស្ស ពន្យាពេលការប្តឹងផ្តល់ និងធ្វើចំណាកស្រុក។ អ្វីៗត្រូវបានបាត់បង់។ ជំងឺត្រូវបានគេមើលឃើញ។ ផ្នូរ Ji Xingshan គឺល្អ។", "古人": "Jiang Taigong ជួបស្តេច Wen", "第X籤": "ឆ្នោតទីម្ភៃដំបូង", "宮": "តាស៊ូមី"}