{"籤詩版本二": "គុណធម៌​ពី​ឪពុក​ដល់​កូន​ត្រូវ​បាន​បន្សល់​ទុក​ដល់​ចៅ​ប្រុស ភាព​រុងរឿង​ខាង​អាហារ និង​សម្លៀក​បំពាក់​អាស្រ័យ​តែ​លើ​ព្រះ​ប៉ុណ្ណោះ។\nChunxuan នៅ​ក្នុង​សាល​ធ្វើ​ឱ្យ​មនុស្ស​សប្បាយ​ចិត្ត ពេល​ពួក​គេ​ស្រេក​ឃ្លាន ស្រេក​ទឹក និង​ងងុយ​គេង Chunxuan ជា​ពាក្យ​ប្រៀបធៀប​សម្រាប់​ឪពុក​ម្តាយ។", "詩意": "hexagram នេះត្រូវបានភ្ជាប់ជាមួយនឹងរូបភាពនៃឫស្សីដែលនាំទៅដល់និទាឃរដូវ។\nសង្ឃឹមថាអ្វីៗដំណើរការល្អ។", "解曰": "យកឬស្សីនាំទៅនិទាឃរដូវ។ វារីករាលដាលគ្មានទីបញ្ចប់។ សុភាពបុរសស្វែងរកក្តីសង្ឃឹម។ ទាំងអស់រីករាយ។", "籤詩故事一": "◇ ស្តេច Wu នៃ Zhou បានឡើងសោយរាជ្យ\nស្តេច Wu នៃ Zhou បានវាយលុកស្តេច Zhou ហើយបានដឹកនាំព្រះអង្គម្ចាស់ចំនួនប្រាំបីរយនាក់ដើម្បីប្រយុទ្ធប្រឆាំងនឹងកងទ័ពរបស់ស្តេច Shang ។ ទាហាននៅ Chaoge (រាជធានីរបស់ស្តេច Shang) ក៏បានងាកមកប្រឆាំងនឹងស្តេច Shang ហើយបានក្បត់ស្តេច Shang ។\nស្តេចចូវបានដុតខ្លួនឯងនៅលើប៉ម Zhaixing ហើយរាជវង្ស Shang ត្រូវបានបំផ្លាញ។\nស្ដេច Wu ទទួល​យក​សៀវភៅ​មាស និង​កំណប់​មាស​ដែល​ជា​បល្ល័ង្ក​របស់​ព្រះចៅ​អធិរាជ ទ្រង់​បែរ​មុខ​ទៅ​ទិស​ខាង​ត្បូង ដៃ​របស់​គាត់​ត្រូវ​បាន​បត់​ចុះ ហើយ​ទ្រង់​ក៏​អង្គុយ​ត្រង់។ ស្តេច Wu បានបញ្ជាឱ្យចែកចាយទ្រព្យសម្បត្តិរបស់ Lutai, អគារ Star Picking Tower ត្រូវកម្ទេចចោល ហើយគ្រាប់ស្រូវដែលរក្សាទុកក្នុង Juqiao ត្រូវចែកចាយ។\nដោះលែង Jizi ដែលជាប់គុក ហើយជួសជុលផ្នូររបស់ Bigan ។ ស្តេច Wu ជិះតាមទ្វារផ្ទះរបស់ Shang Rong ហើយអោនក្បាល។ គោរព​អ្នក​ដែល​មាន​គុណធម៌ ហើយ​លាចាក​បាវ​ក្នុង​វាំង​ខាង​ក្នុង។\nគាត់ក៏បានបញ្ឈប់អាវុធ និងលើកកម្ពស់វប្បធម៌ និងការអប់រំផងដែរ។ នៅ​ភាគ​ខាង​ត្បូង​នៃ​ទីក្រុង Nanshan សេះ​ត្រូវ​បាន​ស៊ីស្មៅ និង​គោ​ក្របី​ស៊ី​ស្មៅ​នៅ​ទី​ជនបទ​ដោយ​មាន​ដើម​ពោធិ៍​ជា​ទិដ្ឋភាព​សន្តិភាព។", "聖意": "ផ្ទះ​មិន​ល្អ​(​សំណាងល្អ​)​អាច​ធ្វើ​បាន​តាម​បំណង​(​លាភ​សំណាង​) រក​ចំណូល​បាន​លុយកាក់​ធ្វើ​ជំនួញ​និង​រៀប​ការ​(​បាន​ជួប​កូនប្រសា​ល្អ​) លី​ចូ​វ​បាន​សុខ​(​រាសី​ល្អ​)​។ sign), ថ្មើរជើងរើស្រែ, ដង្កូវនាងមានសំណាង, សត្វទាំង ៦ ខូច, មនុស្សពិបាករក (មើល) ពាក្យប្ដឹងសាធារណៈ, បុគ្គលខ្ពង់ខ្ពស់ធ្វើចលនា, សំណាងល្អ បាត់ជំងឺ និងជំងឺ", "古人": "ស្តេច Wu នៃ Zhou បានឡើងសោយរាជ្យ", "第X籤": "ទី៥០ ឈ្នះឆ្នោត (ឆ្នោត)", "宮": "វិមានអាក្រក់"}