{"籤詩版本二": "කේක් මත ඇති අයිසිං වඩාත් වර්ණවත් වන අතර, වාසනාව වාසනාව හා වාසනාව ගෙන එයි.\nතමන් ජීවිතයේ ප්‍රමාද වී ප්‍රසිද්ධියට පත් වී එක පහරින් ලොව පුරා ප්‍රසිද්ධියට පත් වීම ගැන එකල මිනිසුන් පසුතැවිලි විය යුතු නැත.", "詩意": "මෙම hexagram යනු කේක් මත අයිසිං වේ.\nසෑම දෙයකම වාසනාව.", "解曰": "පැරණි දේ අලුත් වෙනවා. නිමි ද්රව්ය වෙත නැව්ගත කරන්න. එබැවින් ඔහුගේ ජීවන අභිලාෂය. සියල්ල ඉරණමයි.", "籤詩故事一": "◇Liang Haodengke\nවිශාරද, Liang Hao (963-1004), අනුග්‍රහය සහිත නම Taisu, සෝං රාජවංශයේ Xucheng, Yunzhou (දැන් Dongping, Shandong) හි උපත ලැබීය.\nයොන්ග්සිගේ පාලන සමයේදී ඔහු වයස අවුරුදු දහඅටේදී ජින්ෂි විභාගය සමත් විය. විභාගය සඳහා දිගටම අයදුම් කිරීම අසාර්ථක විය.\nඔහු Tianfu තුන්වන වසරේ විභාගයට පෙනී සිටීමට පටන් ගත්තේය.ඔහු පසුකාලීන හැන් රාජවංශය සහ පසුකාලීන Zhou රාජවංශය හරහා සෑම වසරකම විභාගය සමත් වූ නමුත් සෑම වසරකම අසමත් විය. ප්‍රථම ත්‍යාගය නොදුන්නොත් සමාදාන වෙන්නේ නෑ කියලා දිවුරලා කිව්වා.\nවයස අවුරුදු අසූ දෙකේදී, සොං රාජවංශයේ ෂෙන්සොං අධිරාජ්‍යයාගේ යොන්ග්සි පාලන සමයේ දෙවන වසරේ, ඔහු පළමු ත්‍යාගය දිනා ගත්තේය.", "聖意": "නිවසේ ආරක්ෂාව (ශුභ), පුද්ගලික ආරක්ෂාව, මූල්‍යමය වාසි, ගනුදෙනු, විවාහය, ලියුජියා, පිරිමි පදිකයින්, චිටියානු සේද පණුවන්, කරුණු අටක්, සතුන් හයක්, මිනිසුන් සෙවීම, පොදු නඩු, සංක්‍රමණය, නැතිවූ දේපල, වයඹදිග රෝග, ෆුෂාන් සොහොන් ප්‍රතිලාභ සඳහා යාච්ඤා කරන්න", "古人": "ලියං හෝඩෙන්කේ", "第X籤": "හතළිස් හතක් අත්සන් කරන්න", "宮": "හයිගොං"}