{"籤詩版本二": "කටු වනාන්තරයකින් වට වූ සැඟවීමට කෙලින්ම ද්විත්ව ගොඩනැගිල්ලට යන්න\nTian Gaojun ට දිගු ජීවිතයක් සහ කෙටි ජීවිතයක් ඇත. එක සාර්ථකත්වයක් ලබා ගෙන පුද්ගලයන් දෙදෙනෙකු අහිමි කරන්න. වටේ යන්න →.", "詩意": "මෙම hexgram යනු දේවල් පැරණි ලෙස තබා ගැනීම සහ ඕනෑම වේලාවක වෙනස් කිරීම පිළිබඳ ලකුණකි.\nනියම වේලාව එනතුරු බලා සිටියහොත් සියල්ල සුබ වේ.", "解曰": "හරියට බීල බීල වගේ. හුදෙක් ගතානුගතික වන්න. වෙලාව එනකම් ඉන්න. විපතක් නැත, දොස් නැත.", "籤詩故事一": "◇ Zhang Liangyin කන්ද\nහන් රාජවංශයේ, Zhang Liang, ඔහුගේ අනුග්‍රහය ලෙස Zifang නම්, කොරියානු ජාතිකයෙකි.ඔහුගේ මුතුන් මිත්තන් පරම්පරා පහක් මුළුල්ලේම කොරියානු අගමැතිවරුන් විය.\nQin රාජ්‍යය දකුණු කොරියාව විනාශ කරන විට, Zhang Liang තම සියලු ධනය විසුරුවා හැර සැඟවී ගියේය.දකුණු කොරියාවෙන් පළිගැනීමට අවශ්‍ය වූ ඔහු තම සිරුරේ යකඩ කේතුවක් සහිත ශක්තිමත් මිනිසෙකු යවා ඇත. බොලැන්ග්ෂා (දැන් යුවාන්යැං ප්‍රාන්තයේ, හෙනාන් පළාත) හි ක්වින් ෂිහුආන්ග්ට පහර දෙමින් ඔහු අහම්බෙන් නියෝජ්‍ය මෝටර් රථයට පහර දුන්නේය. පළමු අධිරාජ්‍යයාට ෂැං ලියැංව රට පුරා අත්අඩංගුවට ගැනීමට අවශ්‍ය වූ නමුත් මාස දහයක් යනතුරු ඔහුව අල්ලා ගැනීමට නොහැකි විය.\nපසුව, Zhang Liang ලෝකය එක්සත් කිරීමට හන් රජුට සහාය විය. ඔහුගේ සාර්ථකත්වයෙන් පසු, ඔහු ත්‍යාග පිරිනැමීම ප්‍රතික්ෂේප කර නිලධාරියෙකු පත් කළ අතර, චිසොංසි (අමරණීය) ගෙන් තාඕවාදය ඉගෙනීමේ මුවාවෙන්.", "聖意": "නිවසේ ආශීර්වාද සහ ඔබේ ආරක්ෂාව සඳහා යාච්ඤා කරන්න (මන්දගාමී වාසනාව කරුණාවෙන් පමණක් පැහැදිලි කළ හැකිය) ධනය සෙවීම සාමාන්‍ය දෙයකි (වැළැක්විය යුතුය) ගනුදෙනු සාර්ථක වනු ඇත (විනාඩියක් රැඳී සිටින්න) විවාහය ලියුජියා සමඟ නොගැලපේ, සංචාරය කිරීමේදී වාසනාව ක්ෂේත්‍රය, සේද පණුවන් අර්ධ ශුභයි, සතුන් හය දෙනෙක් සමෘද්ධිමත් (අසාර්ථකයි), මිනිසුන් සෙවීම, පොදු නඩු වලට බාධා, පාඩු, සංක්‍රමණය සුබයි (අවාසනාවන්ත) ) දේපළ අහිමිවීම්, අසනීප සඳහා අසුබ, කඳු සහ සොහොන් වල වාසනාව", "古人": "Zhang Liangyin කන්ද", "第X籤": "පනස් නවය කුසපත් ඇදීම (ලොතරැයිය)", "宮": "යින් මාලිගය"}