{"籤詩版本二": "松や檜が生い茂り、雨、雪、風、霜もすべて耐えられます。\n将来は突然大活躍し、名声が柱となる。", "詩意": "この卦は、松や檜が生い茂る森のようなものです。\nすべてに高貴さがあります。", "解曰": "道中頑張ってください。生涯功労者。野蚕が熟してきました。家族は裕福です。", "籤詩故事一": "◇范文正は、お粥をまぐって汲むことにした\n宋代の有名な役人、范仲燕は貧しい家庭に生まれ、幼い頃は長白山の僧房で学び、毎日2リットルの黍を入れたお粥を炊き、一晩固まってから切りました。包丁で４つに切り分け、朝晩２つずつ食べ、漬物も切って食べた。\nこれは、困難を恐れず、懸命に勉強し、やがて大きな才能を発揮する人を表すために使用されます。\nハローを切り落としてお粥を汲む", "聖意": "家寨は、自分にとって縁起が良い、富を求める、平和、商売、結婚、成功、六家、男性歩行者、信託田、蚕、六家畜、被害、人物追跡、訴訟、移住、遺失物、病気、鞍山墓、縁起", "古人": "范文正は馬車を掘って粥を汲むことにしました", "第X籤": "8番目のサイン", "宮": "醜い宮殿"}