{"籤詩版本二": "ບໍ່​ຕ້ອງ​ກັງ​ວົນ​ກ່ຽວ​ກັບ​ການ​ເຈັບ​ປ່ວຍ​ແລະ​ການ​ຟ້ອງ​ຮ້ອງ​ໃນ​ປັດ​ຈຸ​ບັນ​, ທີ່​ດິນ​ສົມ​ກຽດ​ແລະ​ຄວາມ​ຮັ່ງ​ມີ​ມີ​ທັງ​ຫມົດ​.\nຄື​ກັນ​ກັບ​ຝູງ​ສັດ​ທີ່​ຖືກ​ປົດ​ປ່ອຍ​ຈາກ​ຕ່ອງ​ໂສ້​ຂອງ​ມັນ ແລະ​ກັບ​ຄືນ​ໄປ​ທີ່​ຖ້ຳ​ເພື່ອ​ເດີນ​ທາງ​ໄປ​ມາ", "詩意": "hexagram ນີ້ສະແດງເຖິງຮູບພາບຂອງ ape ທີ່ຖືກປ່ອຍອອກມາຈາກຕ່ອງໂສ້ຂອງມັນ.\nທຸກສິ່ງທຸກຢ່າງແມ່ນຍາກກ່ອນທີ່ມັນຈະງ່າຍຕໍ່ມາ.", "解曰": "ກໍາຈັດສິ່ງຕ່າງໆ. ແລະສະບາຍໃຈ. ມາຕາມເວລາກຳນົດ. ຊອກຫາເສັ້ນທາງທີ່ຖືກຕ້ອງ.", "籤詩故事一": "◇ Xiangzi ພົບ​ຜູ້​ເຂົ້າ​ຮ່ວມ (Han Xiangzi ພົບ Lu Dongbin​)\n​ໃນ​ລາຊະວົງ​ຖາງ, Han Xiangzi ​ແມ່ນ​ຫລານ​ຊາຍ​ຂອງ Han Yu. ລາວມີລັກສະນະເສີຍໆ ແລະຮຽນບໍ່ເກັ່ງ, ສະນັ້ນ ລາວຈຶ່ງບໍ່ມີທາງເລືອກ ນອກຈາກດື່ມເຫຼົ້າ. ລາວ​ໄດ້​ຖືກ​ເອີ້ນ​ໂດຍ Han Yu ໄປ​ຮຽນ​ຢູ່​ໂຮງ​ຮຽນ, ແຕ່​ແທນ​ທີ່​ຈະ​ຮຽນ​ເກັ່ງ, ລາວ​ໄດ້​ຂົ່ມ​ເຫັງ​ເພື່ອນ​ຮ່ວມ​ຫ້ອງ. ຕໍ່​ມາ​, Han Yu ໄດ້​ຈັດ​ໃຫ້​ເຂົາ​ໄປ​ສຶກ​ສາ​ຢູ່​ໃນ​ວັດ​, ແຕ່​ອະ​ທິ​ບໍ​ດີ​ຂອງ​ວັດ​ໄດ້​ຈົ່ມ​ວ່າ​ຕົນ​ຈອງ​ຫອງ​.\nຕໍ່​ມາ, Lu Dongbin ໄດ້​ເຂົ້າ​ມາ​ເຮັດ​ໃຫ້​ລາວ​ຮູ້​ຈັກ, ແລະ​ໃນ​ທີ່​ສຸດ​ລາວ​ໄດ້​ກາຍ​ເປັນ​ອະ​ມະ​ຕະ. ມີ​ຊື່​ວ່າ Emperor Yaohua​. ຫນຶ່ງໃນແປດອະມະຕະ. ສັນຍາລັກຂອງມັນແມ່ນກະຕ່າດອກໄມ້ທີ່ຖືດ້ວຍມື.", "聖意": "ຂ້ອຍ​ຢູ່​ເຮືອນ​ບໍ່​ສະບາຍ, ຂ້ອຍ​ອະທິຖານ​ຂໍ​ຄວາມ​ຮັ່ງມີ​ແລະ​ໂຊກ​ດີ, ການ​ຄ້າ​ຍັງ​ຄ້າງ​ຢູ່, ການ​ແຕ່ງ​ງານ​ບໍ່​ສຳ​ເລັດ, Liujia ອະທິຖານ​ຂໍ​ໃຫ້​ຄົນ​ຍ່າງ​ມາ​ໄຮ່​ທົ່ງນາ, ມີ​ຜ້າ​ໄໝ​ອຸດົມສົມບູນ, ​ໃນ​ບ້ານ Liu ​ໄດ້​ພົບ​ເຫັນ​ການ​ຟ້ອງ​ຮ້ອງ​ຂອງ​ປະຊາຊົນ. ຖືກ​ຕ້ອງ, ຊັບ​ສິນ​ທີ່​ສູນ​ເສຍ​ໄປ​ຢູ່​ຫ່າງ​ໄກ​, ພະ​ຍາດ​ແມ່ນ​ໂຊກ​ບໍ່​ດີ​, ຝັງ​ສົບ Anshan ເປັນ​ຄວາມ​ສຸກ​", "古人": "Xiangzi ພົບ​ຜູ້​ເຂົ້າ​ຮ່ວມ (Han Xiangzi ພົບ Lu Dongbin​)", "第X籤": "ຫວຍສາມສິບຫົກ", "宮": "Shen Gong"}