{"籤詩版本二": "राम्रो प्रदर्शनले तपाईंलाई भीडबाट एक भ्रामक रूपमा खडा बनाउँछ, र तपाईंको भविष्य परिवर्तन हुन्छ र तपाईंले धेरै धन ल्याउनुहुन्छ।\nबाटो आकाश जत्तिकै फराकिलो छ, र तपाईंले दिन सक्ने सबै पैसा तपाईंको हृदयमा हुनेछ", "詩意": "यो हेक्साग्रामले आशाजनक भविष्यलाई संकेत गर्छ।\nसबै कुरा राम्ररी चल्छ।", "解曰": "ठूलो बाटो। तपाईं अगाडि बढ्न सक्नुहुन्छ। आफ्नो हृदय प्रयोग गर्नुहोस्। अगाडि मात्र।\nसबै कुरा यो चिन्ह संग योजना अनुसार जान्छ। Jichang को शुभकामना।", "籤詩故事一": "◇ तीन नायकहरू लु बु विरुद्ध लड्छन्\nसमाधान: तीन नायक झांग फेई, गुआन यू, र लिउ बेई लु बु विरुद्ध लड्छन्\nडोङ झुओले थाहा पाए कि Hua Xiong को टाउको काटिएको थियो र फ्लाइङ जनरल लु बु लाई युद्ध गर्न पठाइएको थियो। लु बु युद्धमा जाने बित्तिकै, उनले सेनापति फाङ यू र मु शुनलाई मारे र वू आंगुओ र गोंग्सुन जानलाई मारे।\nझांग फेईले देखे कि गोंग्सुन जानले लु बुलाई हराउन सक्दैनन्, त्यसैले उनले तुरुन्तै गोंग्सुन जानलाई प्रतिस्थापन गरे र कराए: \"तीन थरका दासहरू छोड्नुपर्छ! यानबाट झांग फेई यहाँ छ!\" त्यसपछि, तिनीहरूले पचास राउन्ड भन्दा बढी लडे। उत्तराधिकार, कुनै विजेता वा हारे बिना।\nगुआन यूले यो देखेपछि, उनले र झांग फेईले लु बुमाथि आक्रमण गरे र तीस राउन्ड भन्दा बढी लडे।\nलिउ बेईले पनि दुई तरवार बोके, घोडाले ताली बजाए र झाङ फेई र गुआन यूलाई मद्दत गर्न अगाडि बढे।\nतीन जनाले लुबुलाई घेरे र लडाइँ गरिरहे, समूहका सबै मानिसहरू स्तब्ध भए।\nचाँडै, लु बुले बल गुमाउन थाले।लु बुको पेगासस पछि हट्यो, तर तीन जना मानिसहरूले लु बुलाई पछ्याए र हार मानेनन्।उनीहरूले लु बुको सेनालाई नभेटेसम्म पछि हटेनन्।\n\"तीन राज्यहरू\"\n(यो कथा लु बुको बहादुरी र लडाइँमा सीपको रूपक हो। एक व्यक्तिले तीन जनालाई हराउन सक्छ।)", "聖意": "घर र घरको मुटु मात्र धन खोज्नको लागि आफ्नै यात्रामा जान्छ। सम्भावित विवाह लेख लिउजियामा जान्छ। चीजहरू मानिसहरूको लागि सहज रूपमा जान्छन्। झुशुन्टियन रेशमकीराहरू प्रयोग गर्छन्। मानिसहरू छवटा जनावरहरू मध्ये भेट्टाउन सकिन्छ। सार्वजनिक मुद्दा अघि, यिछाङ बसाइँसराइ, हराएको सम्पत्ति, रोग, पहाडको चिहान आदि शुभ हुन्छ ।", "古人": "तीन नायकहरू लु बु विरुद्ध लड्छन्", "第X籤": "लटरी नब्बे एक जित्दै", "宮": "तिमी दरबार"}