{"籤詩版本二": "불멸의 바위로 바로 가서 불멸을 배우고, 이 지식이 황제에 의해 선포되면,\n푸른 하늘과 해와 달은 언제나 밝게 빛나고, 의로운 마음의 명성이 온 세상에 퍼집니다.", "詩意": "이 육각형은 고귀한 사람들의 인도를 받는 상징입니다.\n모든 것이 잘 어울립니다.", "解曰": "시작과 끝이 있습니다. 서쪽이나 동쪽으로 가지 마십시오. 마음을 사용하십시오. 고귀한 사람들이 많이 있습니다.", "籤詩故事一": "◇류즈위안, 군대로 탈북\nLiu Zhiyuan (Zhiyuan)은 Shatao (Shatuo 부족) 출신이었습니다.\nLiu Zhiyuan과 그의 아내 Li Sanniang은 삼촌 집에 살았는데, 그의 삼촌은 Liu Zhiyuan (Zhiyuan)이 가난하다고 의심하여 ​​Liu가 두 멜론 정령에게 먹히기를 바라며 Zhiyuan을 설득하여 멜론 정원에 갔습니다. 밤에 총을 쏘고 멜론 정령들과 싸우고 지하로 들어가 땅을 파고 검과 전쟁서를 가져오라.\n검과 무술을 익히고 아내와 작별하고 군대에 입대하여 월순과 함께 피난하여 회유사신의 관리로 복무하였다.\n거란은 진나라를 멸망시키고 중원에는 주인이 없게 하였으며, 지원은 진양에서 황제가 되었습니다.\n나라가 후한(後한)나라로 바뀌었다. 연호를 바꾸지 않고 여전히 천부(十富)라고 부른다.", "聖意": "집이 평안하고, 사업이 잘되고, 돈이 잘 벌고, 사업이 잘되고, 결혼이 잘되고, 부부가 결혼하고, 남자 나그네가 밭으로 돌아오고, 누에를 반쯤 수확하고, 여섯 마리의 동물이 성공한다 , 사람을 찾았다, 소송이 성공했다, 이주가 좋다, 유실물이 좋다, 질병이 안산이다, 묘가 좋다", "古人": "류즈위안, 군대로 탈북", "第X籤": "80번째 기호", "宮": "웨이 공"}